AUTHORS
CHANGES
LICENSE
MANIFEST.in
Makefile
README
logo.svg
setup.cfg
setup.py
tox.ini
docs/html/api.html
docs/html/genindex.html
docs/html/index.html
docs/html/intro.html
docs/html/markup.html
docs/html/objects.inv
docs/html/project.html
docs/html/py-modindex.html
docs/html/search.html
docs/html/searchindex.js
docs/html/signals.html
docs/html/_sources/api.rst.txt
docs/html/_sources/index.rst.txt
docs/html/_sources/intro.rst.txt
docs/html/_sources/markup.rst.txt
docs/html/_sources/project.rst.txt
docs/html/_sources/signals.rst.txt
docs/html/_sources/patterns/index.rst.txt
docs/html/_sources/patterns/widgets.rst.txt
docs/html/_sources/schema/arrays.rst.txt
docs/html/_sources/schema/compound.rst.txt
docs/html/_sources/schema/datetimes.rst.txt
docs/html/_sources/schema/declarative.rst.txt
docs/html/_sources/schema/dicts.rst.txt
docs/html/_sources/schema/enums.rst.txt
docs/html/_sources/schema/exceptions.rst.txt
docs/html/_sources/schema/index.rst.txt
docs/html/_sources/schema/lists.rst.txt
docs/html/_sources/schema/properties.rst.txt
docs/html/_sources/schema/references.rst.txt
docs/html/_sources/schema/scalars.rst.txt
docs/html/_sources/schema/schema.rst.txt
docs/html/_sources/schema/traversal.rst.txt
docs/html/_sources/validation/api.rst.txt
docs/html/_sources/validation/basic.rst.txt
docs/html/_sources/validation/builtin.rst.txt
docs/html/_sources/validation/custom.rst.txt
docs/html/_sources/validation/index.rst.txt
docs/html/_static/basic.css
docs/html/_static/doctools.js
docs/html/_static/documentation_options.js
docs/html/_static/file.png
docs/html/_static/flatland.css
docs/html/_static/flatland.png
docs/html/_static/jquery-3.2.1.js
docs/html/_static/jquery.js
docs/html/_static/language_data.js
docs/html/_static/minus.png
docs/html/_static/plus.png
docs/html/_static/pygments.css
docs/html/_static/searchtools.js
docs/html/_static/underscore-1.3.1.js
docs/html/_static/underscore.js
docs/html/patterns/index.html
docs/html/patterns/widgets.html
flatland.egg-info/PKG-INFO
flatland.egg-info/SOURCES.txt
flatland.egg-info/dependency_links.txt
flatland.egg-info/requires.txt
flatland.egg-info/top_level.txt
flatland.egg-info/zip-safe
